odoo/addons/fieldservice_sale_stock_from_pos/README.rst
odoo/addons/fieldservice_sale_stock_from_pos/__init__.py
odoo/addons/fieldservice_sale_stock_from_pos/__manifest__.py
odoo/addons/fieldservice_sale_stock_from_pos/i18n/ca.po
odoo/addons/fieldservice_sale_stock_from_pos/i18n/es.po
odoo/addons/fieldservice_sale_stock_from_pos/i18n/fieldservice_sale_stock_from_pos.pot
odoo/addons/fieldservice_sale_stock_from_pos/i18n/it.po
odoo/addons/fieldservice_sale_stock_from_pos/models/__init__.py
odoo/addons/fieldservice_sale_stock_from_pos/models/pos_config.py
odoo/addons/fieldservice_sale_stock_from_pos/models/res_config_settings.py
odoo/addons/fieldservice_sale_stock_from_pos/models/sale_order.py
odoo/addons/fieldservice_sale_stock_from_pos/models/stock_picking.py
odoo/addons/fieldservice_sale_stock_from_pos/readme/CONTRIBUTORS.md
odoo/addons/fieldservice_sale_stock_from_pos/readme/DESCRIPTION.md
odoo/addons/fieldservice_sale_stock_from_pos/readme/USAGE.md
odoo/addons/fieldservice_sale_stock_from_pos/static/description/icon.png
odoo/addons/fieldservice_sale_stock_from_pos/static/description/index.html
odoo/addons/fieldservice_sale_stock_from_pos/static/tests/tours/SaleStockFromPosFsmTour.tour.esm.js
odoo/addons/fieldservice_sale_stock_from_pos/static/tests/tours/helpers/SaleStockFromFsmPosMethods.esm.js
odoo/addons/fieldservice_sale_stock_from_pos/tests/__init__.py
odoo/addons/fieldservice_sale_stock_from_pos/tests/common.py
odoo/addons/fieldservice_sale_stock_from_pos/tests/test_fsm_from_pos_in_real_time.py
odoo/addons/fieldservice_sale_stock_from_pos/tests/test_fsm_from_pos_not_in_real_time.py
odoo/addons/fieldservice_sale_stock_from_pos/views/res_config_settings.xml
odoo_addon_fieldservice_sale_stock_from_pos-17.0.1.0.0.4.dist-info/METADATA
odoo_addon_fieldservice_sale_stock_from_pos-17.0.1.0.0.4.dist-info/WHEEL
odoo_addon_fieldservice_sale_stock_from_pos-17.0.1.0.0.4.dist-info/top_level.txt
odoo_addon_fieldservice_sale_stock_from_pos-17.0.1.0.0.4.dist-info/RECORD
