Metadata-Version: 2.1
Name: odoo-addon-fieldservice_sale_stock_from_pos
Version: 17.0.1.0.0.4
Requires-Python: >=3.10
Requires-Dist: odoo-addon-fieldservice>=17.0dev,<17.1dev
Requires-Dist: odoo-addon-fieldservice_sale_stock>=17.0dev,<17.1dev
Requires-Dist: odoo-addon-pos_order_to_sale_order>=17.0dev,<17.1dev
Requires-Dist: odoo>=17.0a,<17.1dev
Summary: Create Field Service Orders from POS Orders
Home-page: https://github.com/OCA/field-service
License: AGPL-3
Author: APSL- Nagarro, Odoo Community Association (OCA)
Author-email: support@odoo-community.org
Classifier: Programming Language :: Python
Classifier: Framework :: Odoo
Classifier: Framework :: Odoo :: 17.0
Classifier: License :: OSI Approved :: GNU Affero General Public License v3
